pp_python_utils/__init__.py
pp_python_utils/py.typed
pp_python_utils/result.py
pp_python_utils-1.0.4.dist-info/METADATA
pp_python_utils-1.0.4.dist-info/WHEEL
pp_python_utils-1.0.4.dist-info/RECORD
