Metadata-Version: 2.1
Name: pp-python-utils
Version: 1.0.4
Summary: Internal python utility library
Author: Shahak
Author-email: yaakov@lightricks.com
Requires-Python: >=3.12,<4.0
Classifier: Programming Language :: Python :: 3
Classifier: Programming Language :: Python :: 3.12
Requires-Dist: pydantic (==2.8.2)
